[
    {
        "channel_name": "& Pictures",
        "channel_logo": "https://i.postimg.cc/J42g7Wgz/pictures.png",
        "channel_links": [
            {
                "link_title": "& Pictures",
                "channel_url": "221260.m3u8",
                "link_type": "opplex"
            }
        ]
    },
    {
        "channel_name": "7S Music (576p)",
        "channel_logo": "https://i.postimg.cc/tCKdHGtc/images-12.jpg",
        "channel_links": [
            {
                "link_title": "7S Music (576p)",
                "channel_url": "http://103.199.161.254/Content/7smusic/Live/Channel(7smusic)/index.m3u8",
                "link_type": "none"
            }
        ]
    },
    {
        "channel_name": "9XM (480p)",
        "channel_logo": "https://logos-download.com/wp-content/uploads/2020/06/9XM_Logo.png",
        "channel_links": [
            {
                "link_title": "9XM (480p)",
                "channel_url": "https://d35j504z0x2vu2.cloudfront.net/v1/manifest/0bc8e8376bd8417a1b6761138aa41c26c7309312/9xm/9f1a3d57-4134-4f4c-95ea-2cb142ac63f8/0.m3u8",
                "link_type": "none"
            }
        ]
    },
    {
        "channel_name": "Animal Planet",
        "channel_logo": "https://upload.wikimedia.org/wikipedia/commons/3/3e/Animal_Planet.png",
        "channel_links": [
            {
                "link_title": "Animal Planet",
                "channel_url": "206282.m3u8",
                "link_type": "opplex"
            }
        ]
    },
    {
        "channel_name": "Aaj Tak",
        "channel_logo": "https://upload.wikimedia.org/wikipedia/commons/2/28/Aaj_tak_logo.png",
        "channel_links": [
            {
                "link_title": "Aaj Tak",
                "channel_url": "https://aajtaklive-amd.akamaized.net/hls/live/2014416/aajtak/aajtaklive/live_404p/chunks.m3u8",
                "link_type": "none"
            },
            {
                "link_title": "Aaj Tak",
                "channel_url": "244915.m3u8",
                "link_type": "opplex"
            }
            
        ]
    },
    {
        "channel_name": "B4U Music",
        "channel_logo": "https://i.postimg.cc/NFPpJst2/B4-U-Music-logo-2014.png",
        "channel_links": [
            {
                "link_title": "B4U Music",
                "channel_url": "https://d3kdywbtdfbp9z.cloudfront.net/v1/manifest/93ce20f0f52760bf38be911ff4c91ed02aa2fd92/dff423e0-3c82-46d6-9ecb-3baa96b5694a/4598c408-0e38-488c-9b64-fc845d1ea2b6/0.m3u8",
                "link_type": "none"
            }
        ]
    },
    {
        "channel_name": "Balle Balle",
        "channel_logo": "https://i.postimg.cc/wxWfTVNx/Balle-Balle-TV.png",
        "channel_links": [
            {
                "link_title": "Balle Balle",
                "channel_url": "https://mcncdndigital.com/balleballetv/index.m3u8",
                "link_type": "none"
            }
        ]
    },
    {
        "channel_name": "B4U Movies",
        "channel_logo": "https://i.postimg.cc/YCLyPWhr/B4-U-MOVIES-2014.png",
        "channel_links": [
            {
                "link_title": "B4U Movies",
                "channel_url": "104201.m3u8",
                "link_type": "opplex"
            }
        ]
    },
    {
        "channel_name": "Bflix Movies",
        "channel_logo": "https://i.postimg.cc/ZK2w65j1/Bflix-Movies-Logo.png",
        "channel_links": [
            {
                "link_title": "Bflix Movies",
                "channel_url": "104190.m3u8",
                "link_type": "opplex"
            }
        ]
    },
    {
        "channel_name": "Colors Cineplex",
        "channel_logo": "https://jiotvimages.cdn.jio.com/dare_images/images/Color_Cineplex_HD.png",
        "channel_links": [
            {
                "link_title": "Colors Cineplex",
                "channel_url": "104191.m3u8",
                "link_type": "opplex"
            }
        ]
    },
    {
        "channel_name": "Desi Tv",
        "channel_logo": "https://i.postimg.cc/43TwF2DP/227-2276139-desi-channel-logo-desi-channel.png",
        "channel_links": [
            {
                "link_title": "Desi Tv",
                "channel_url": "https://d35j504z0x2vu2.cloudfront.net/v1/master/0bc8e8376bd8417a1b6761138aa41c26c7309312/desi-tv/master.m3u8",
                "link_type": "none"
            }
        ]
    },
    {
        "channel_name": "Discovery",
        "channel_logo": "https://i.postimg.cc/4xH0mSkb/Discovery-Inc-Logo-wine.png",
        "channel_links": [
            {
                "link_title": "Discovery",
                "channel_url": "https://atemecdnbalancer-voe.sysln.id/live/eds/DiscoveryHD/mpd/DiscoveryHD.mpd?|drmScheme=clearkey&drmLicense=00cff33589a6468eb98e4db7aad46ca0:53bb2de4f3a4ed84661e4fc527a1fc09",
                "link_type": "none"
            }
        ]
    },
    {
        "channel_name": "Discovery Kids",
        "channel_logo": "https://upload.wikimedia.org/wikipedia/commons/6/62/Discovery_kids_logo.png",
        "channel_links": [
            {
                "link_title": "Discovery Kids",
                "channel_url": "76723.m3u8",
                "link_type": "opplex"
            }
        ]
    },
    {
        "channel_name": "Disney Channel",
        "channel_logo": "https://i.postimg.cc/k5FwrF9m/Disney-Channel-Germany-Logo-2014.png",
        "channel_links": [
            {
                "link_title": "Disney Channel",
                "channel_url": "346464.m3u8",
                "link_type": "opplex"
            }
        ]
    },
    {
        "channel_name": "Enter 10 Bangla",
        "channel_logo": "https://i.postimg.cc/rmVjq0Ft/Enterr10-Bangla-logo-2020.png",
        "channel_links": [
            {
                "link_title": "Enter 10 Bangla",
                "channel_url": "245954.m3u8",
                "link_type": "opplex"
            }
        ]
    },
    {
        "channel_name": "Enter 10 Movies",
        "channel_logo": "https://static.wikia.nocookie.net/logopedia/images/f/f3/Enterr10_logo.png",
        "channel_links": [
            {
                "link_title": "Enter 10 Movies",
                "channel_url": "104202.m3u8",
                "link_type": "opplex"
            }
        ]
    },
    {
        "channel_name": "Goldmines",
        "channel_logo": "https://i.postimg.cc/SRjGzB9S/goldmines-telefilms-advertisements-services.png",
        "channel_links": [
            {
                "link_title": "Goldmines",
                "channel_url": "112972.m3u8",
                "link_type": "opplex"
            }
        ]
    },
    {
        "channel_name": "Hungama",
        "channel_logo": "https://i.postimg.cc/x873G6GK/Hungama-TV.png",
        "channel_links": [
            {
                "link_title": "Hungama",
                "channel_url": "150480.m3u8",
                "link_type": "opplex"
            }
        ]
    },
    {
        "channel_name": "Jalsha Movies",
        "channel_logo": "https://i.postimg.cc/dQS6K0ML/Jalsha-Movies-HD-alt.png",
        "channel_links": [
            {
                "link_title": "Jalsha Movies",
                "channel_url": "245900.m3u8",
                "link_type": "opplex"
            }
        ]
    },
    {
        "channel_name": "Khushboo Bangla",
        "channel_logo": "https://i.postimg.cc/sDQcfRyK/Khushboo-Bangla-logo-2017.png",
        "channel_links": [
            {
                "link_title": "Khushboo Bangla",
                "channel_url": "https://cdn3.pishow.tv/live/283/master.m3u8",
                "link_type": "none"
            }
        ]
    },
    {
        "channel_name": "MTV",
        "channel_logo": "https://upload.wikimedia.org/wikipedia/commons/6/68/MTV_2021_%28brand_version%29.svg",
        "channel_links": [
            {
                "link_title": "MTV",
                "channel_url": "http://14.102.123.50:5001/live/248.m3u8",
                "link_type": "none"
            }
        ]
    },
    {
        "channel_name": "MTV Beats",
        "channel_logo": "https://upload.wikimedia.org/wikipedia/commons/3/33/MTV_Beats_Logo.png",
        "channel_links": [
            {
                "link_title": "MTV Beats",
                "channel_url": "66273.m3u8",
                "link_type": "opplex"
            }
        ]
    },
    {
        "channel_name": "Music India",
        "channel_logo": "https://i.postimg.cc/Twn3jBVd/Music-India.png",
        "channel_links": [
            {
                "link_title": "Music India",
                "channel_url": "190028.m3u8",
                "link_type": "opplex"
            }
        ]
    },
    {
        "channel_name": "Mon Tv",
        "channel_logo": "https://i.postimg.cc/SNQqCqyh/1708ecea-d867-423c-9743-2aabefcd8ecc.jpg",
        "channel_links": [
            {
                "link_title": "Mon Tv",
                "channel_url": "https://live-stream.utkalbongo.com/utkalbongo/stream7/hls/montvlivestream.m3u8",
                "link_type": "none"
            }
        ]
    },
    {
        "channel_name": "Manoranjan Movies",
        "channel_logo": "https://i.postimg.cc/V6Zq1KV3/20230407145625.png",
        "channel_links": [
            {
                "link_title": "Manoranjan Movies",
                "channel_url": "104204.m3u8",
                "link_type": "opplex"
            }
        ]
    },
    {
        "channel_name": "Maha Movies",
        "channel_logo": "https://jiotvimages.cdn.jio.com/dare_images/images/Maha_Movies.png",
        "channel_links": [
            {
                "link_title": "Maha Movies",
                "channel_url": "104206.m3u8",
                "link_type": "opplex"
            }
        ]
    },
    {
        "channel_name": "Nick Jr",
        "channel_logo": "https://logos-world.net/wp-content/uploads/2021/09/Nick-Jr.-Logo-2009-present.png",
        "channel_links": [
            {
                "link_title": "Nick Jr",
                "channel_url": "http://xtv.ooo:8080/live/98267/02727/238531.m3u8",
                "link_type": "none"
            }
        ]
    },
    {
        "channel_name": "Sangeet Bhojpuri",
        "channel_logo": "https://upload.wikimedia.org/wikipedia/commons/1/1e/Sangeet_Bhojpuri.jpg",
        "channel_links": [
            {
                "link_title": "Sangeet Bhojpuri",
                "channel_url": "https://d1g8wgjurz8via.cloudfront.net/bpk-tv/Sangeetbhojpuri/default/sangeetbhojpuri-audio_208482_und=208000-video=247600.m3u8",
                "link_type": "none"
            }
        ]
    },
    {
        "channel_name": "Star Jalsha",
        "channel_logo": "https://i.postimg.cc/yN42bNvx/Star-Jalsha-logo-2023.png",
        "channel_links": [
            {
                "link_title": "Star Jalsha",
                "channel_url": "245898.m3u8",
                "link_type": "opplex"
            },
            {
                "link_title": "Star Jalsha ( server 2 )",
                "channel_url": "http://atg100.xyz/live/UL33K17/SYC4T9D/76204.m3u8",
                "link_type": "none"
            }
        ]
    },
    {
        "channel_name": "Star Gold",
        "channel_logo": "https://tvschedule.today/_next/image?url=https%3A%2F%2Fimagesdishtvd2h.whatsonindia.com%2Fdasimages%2Fchannel%2Flandscape%2F360x270%2FM93IDRjM.png&w=256&q=75",
        "channel_links": [
            {
                "link_title": "Star Gold",
                "channel_url": "66177.m3u8",
                "link_type": "opplex"
            }
        ]
    },
    {
        "channel_name": "Star Gold Select",
        "channel_logo": "https://tvschedule.today/_next/image?url=https%3A%2F%2Fimagesdishtvd2h.whatsonindia.com%2Fdasimages%2Fchannel%2Flandscape%2F360x270%2FiwxMxXyV.png&w=256&q=75",
        "channel_links": [
            {
                "link_title": "Star Gold Select",
                "channel_url": "221257.m3u8",
                "link_type": "opplex"
            }
        ]
    },
    {
        "channel_name": "Star Gold Thrills",
        "channel_logo": "https://i.postimg.cc/xT44gRjp/image.png",
        "channel_links": [
            {
                "link_title": "Star Gold Thrills",
                "channel_url": "221258.m3u8",
                "link_type": "opplex"
            }
        ]
    },
    {
        "channel_name": "Star Gold Romance",
        "channel_logo": "https://i.postimg.cc/Df5D4h9T/image.png",
        "channel_links": [
            {
                "link_title": "Star Gold Romance",
                "channel_url": "66186.m3u8",
                "link_type": "opplex"
            }
        ]
    },
    {
        "channel_name": "Star Gold 2",
        "channel_logo": "https://img-cdn.thepublive.com/fit-in/640x430/filters:format(webp)/afaqs/media/post_attachments/41d240a6a57208111c1d55f18e3e947681cc1aaca30c8cfdadff35afa5bf55d9.png",
        "channel_links": [
            {
                "link_title": "Star Gold 2",
                "channel_url": "106133.m3u8",
                "link_type": "opplex"
            }
        ]
    },

     {
        "channel_name": "Sony Aath",
        "channel_logo": "https://upload.wikimedia.org/wikipedia/commons/thumb/5/53/Sony_Aath_logo.svg/1742px-Sony_Aath_logo.svg.png",
        "channel_links": [
            {
                "link_title": "Sony Aath",
                "channel_url": "https://tataplay.slivcdn.com/hls/live/2011641/SonyAathSD/master.m3u8",
                "link_type": "none"
            }
        ]
    },

         {
        "channel_name": "Sony Pal",
        "channel_logo": "https://i.postimg.cc/VNjHF0NJ/image.png",
        "channel_links": [
            {
                "link_title": "Sony pal",
                "channel_url": "https://tataplay.slivcdn.com/hls/live/2011741/SonyPalSD/master.m3u8",
                "link_type": "none"
            }
        ]
    },

         {
        "channel_name": "Sony Marathii",
        "channel_logo": "https://upload.wikimedia.org/wikipedia/en/7/7d/Sony_Marathi.png",
        "channel_links": [
            {
                "link_title": "Sony Marathii",
                "channel_url": "https://tataplay.slivcdn.com/hls/live/2011740/SonyMarathi/master.m3u8",
                "link_type": "none"
            }
        ]
    },

         {
        "channel_name": "Sony Sab",
        "channel_logo": "https://upload.wikimedia.org/wikipedia/en/f/f4/Sony_Sab_new.png",
        "channel_links": [
            {
                "link_title": "Sony Sab",
                "channel_url": "https://tataplay.slivcdn.com/hls/live/2011749/SABHD/master.m3u8",
                "link_type": "none"
            }
        ]
    },

         {
        "channel_name": "Sony Set",
        "channel_logo": "https://i.postimg.cc/66Srm1RZ/SETindialogo-new.png",
        "channel_links": [
            {
                "link_title": "Set Hd",
                "channel_url": "https://tataplay.slivcdn.com/hls/live/2011671/SETHD/master.m3u8",
                "link_type": "none"
            }
        ]
    },

         {
        "channel_name": "Sony Max",
        "channel_logo": "https://upload.wikimedia.org/wikipedia/en/b/b6/Sony_Max_new.png",
        "channel_links": [
        
            {
                "link_title": "Sony Max",
                "channel_url": "https://tataplay.slivcdn.com/hls/live/2011670/SonyMaxhd/master.m3u8",
                "link_type": "none"
            },
            {
                "link_title": "Sony Max",
                "channel_url": "66179.m3u8",
                "link_type": "opplex"
            }
        ]
    },

         {
        "channel_name": "Sony Hd",
        "channel_logo": "https://images-wixmp-ed30a86b8c4ca887773594c2.wixmp.com/f/409efa6e-c69a-4971-ac4e-a2a76dcd02e5/dfg9wj7-0e8e4456-1c71-4aa0-bc54-8136acc429ac.png/v1/fill/w_342,h_437/sony_max_hd_logo__2022_present__by_mattjacks2003_dfg9wj7-fullview.png?token=eyJ0eXAiOiJKV1QiLCJhbGciOiJIUzI1NiJ9.eyJzdWIiOiJ1cm46YXBwOjdlMGQxODg5ODIyNjQzNzNhNWYwZDQxNWVhMGQyNmUwIiwiaXNzIjoidXJuOmFwcDo3ZTBkMTg4OTgyMjY0MzczYTVmMGQ0MTVlYTBkMjZlMCIsIm9iaiI6W1t7ImhlaWdodCI6Ijw9NDM3IiwicGF0aCI6IlwvZlwvNDA5ZWZhNmUtYzY5YS00OTcxLWFjNGUtYTJhNzZkY2QwMmU1XC9kZmc5d2o3LTBlOGU0NDU2LTFjNzEtNGFhMC1iYzU0LTgxMzZhY2M0MjlhYy5wbmciLCJ3aWR0aCI6Ijw9MzQyIn1dXSwiYXVkIjpbInVybjpzZXJ2aWNlOmltYWdlLm9wZXJhdGlvbnMiXX0._utM8C_62bxBbR8tSxW6bNwlJ8t8ncDdDPNXWbNLetE",
        "channel_links": [
            {
                "link_title": "Sony Hd",
                "channel_url": "https://tataplay.slivcdn.com/hls/live/2011745/SonyMaxSD/master.m3u8",
                "link_type": "none"
            }
        ]
    },

         {
         "channel_name": "Sony Max 2",
        "channel_logo": "https://jiotvimages.cdn.jio.com/dare_images/images/Sony_MAX2.png",
        "channel_links": [
             {
                "link_title": "Sony Max 2",
                "channel_url": "https://tataplay.slivcdn.com/hls/live/2011908/MAX2/master.m3u8",
                "link_type": "none"
            },
            {
                "link_title": "Sony Max 2",
                "channel_url": "66189.m3u8",
                "link_type": "opplex"
            }
           
        ]
    },

         {
        "channel_name": "Sony Pix",
        "channel_logo": "https://i.postimg.cc/G2K7W0Gr/Sony-Pix-new-logo.png",
        "channel_links": [
            {
                "link_title": "Sony Pix",
                "channel_url": "https://tataplay.slivcdn.com/hls/live/2011748/PIXHD/master.m3u8",
                "link_type": "none"
            }
        ]
    },

         {
        "channel_name": "Sony WAH",
        "channel_logo": "https://upload.wikimedia.org/wikipedia/hi/5/58/Sony_Wah_new_logo.png",
        "channel_links": [
            {
                "link_title": "Sony WAH",
                "channel_url": "https://tataplay.slivcdn.com/hls/live/2011906/SonyWah/master.m3u8",
                "link_type": "none"
            }
        ]
    },

       {
        "channel_name": "Sony BBC Earth",
        "channel_logo": "https://i.postimg.cc/0yknDXwJ/RnzI34c.png",
        "channel_links": [
            {
                "link_title": "Sony BBC Earth",
                "channel_url": "https://tataplay.slivcdn.com/hls/live/2011907/SonyBBCEarthHD/master.m3u8",
                "link_type": "none"
            }
        ]
    },
    {
        "channel_name": "WOW Cinema One",
        "channel_logo": "https://multireach.in/wp-content/uploads/2020/09/wow-cinema.png",
        "channel_links": [
            {
                "link_title": "WOW Cinema One",
                "channel_url": "106132.m3u8",
                "link_type": "opplex"
            }
        ]
    },
    {
        "channel_name": "Yrf Music",
        "channel_logo": "https://i.postimg.cc/BnvmK7rw/1200px-Yash-Raj-Films-Logo-svg.png",
        "channel_links": [
            {
                "link_title": "Yrf Music",
                "channel_url": "383530.m3u8",
                "link_type": "opplex"
            }
        ]
    },
    {
        "channel_name": "Zoom",
        "channel_logo": "https://i.postimg.cc/Mpwd9F2D/Zoom.png",
        "channel_links": [
            {
                "link_title": "Zoom",
                "channel_url": "https://d75dqofg5kmfk.cloudfront.net/bpk-tv/Zoom/default/index.m3u8",
                "link_type": "none"
            }
        ]
    },
    {
        "channel_name": "Zee Bangla",
        "channel_logo": "https://i.postimg.cc/zGYnJbxX/Zee-Bangla-logo.png",
        "channel_links": [
            {
                "link_title": "Zee Bangla",
                "channel_url": "245893.m3u8",
                "link_type": "opplex"
            },
            {
                "link_title": "Zee Bangla ( Server 2 )",
                "channel_url": "https://smart.bengaldigital.live/Zee-Bangla/index.m3u8",
                "link_type": "none"
            }
        ]
    },
    {
        "channel_name": "Zee TV",
        "channel_logo": "https://upload.wikimedia.org/wikipedia/commons/d/d0/Zee_TV-2018.png",
        "channel_links": [
            {
                "link_title": "Zee TV",
                "channel_url": "221250.m3u8",
                "link_type": "opplex"
            }
        ]
    },
    {
        "channel_name": "Zee Cinema",
        "channel_logo": "https://i.postimg.cc/mZcXk9yQ/Zee-Cinema-logo.png",
        "channel_links": [
            {
                "link_title": "Zee Cinema",
                "channel_url": "206307.m3u8",
                "link_type": "opplex"
            },
            {
                "link_title": "Zee Cinema ( Server 2 )",
                "channel_url": "http://170.254.18.107/ZEECINEMA/index.m3u8",
                "link_type": "none"
            }
        ]
    },
    {
        "channel_name": "Zee Bollywood",
        "channel_logo": "https://i.postimg.cc/kD3tXzFh/clients-logo-zee-bollywood.png",
        "channel_links": [
            {
                "link_title": "Zee Bollywood",
                "channel_url": "207200.m3u8",
                "link_type": "opplex"
            }
        ]
    },
    {
        "channel_name": "Zee Anmol Cinema",
        "channel_logo": "https://i.postimg.cc/L61tKBBb/Zee-Anmol-Cinema.png",
        "channel_links": [
            {
                "link_title": "Zee Anmol Cinema",
                "channel_url": "66187.m3u8",
                "link_type": "opplex"
            }
        ]
    },
    {
        "channel_name": "Zee Classic",
        "channel_logo": "https://i.postimg.cc/zXKxS1Mv/Zeeclassic-new.png",
        "channel_links": [
            {
                "link_title": "Zee Classic",
                "channel_url": "66201.m3u8",
                "link_type": "opplex"
            }
        ]
    },
    {
        "channel_name": "Zee Bangla Cinema",
        "channel_logo": "https://i.postimg.cc/QM05k6hH/Zee-bangla-cinema.png",
        "channel_links": [
            {
                "link_title": "Zee Bangla Cinema",
                "channel_url": "245897.m3u8",
                "link_type": "opplex"
            }
        ]
    }
]
